structura.cpython-38-x86_64-linux-gnu.so
structura-0.3.1.dist-info/METADATA
structura-0.3.1.dist-info/LICENCE
structura-0.3.1.dist-info/WHEEL
structura-0.3.1.dist-info/top_level.txt
structura-0.3.1.dist-info/RECORD
